Netbyte-0.1.6.3.dist-info/METADATA
Netbyte-0.1.6.3.dist-info/RECORD
Netbyte-0.1.6.3.dist-info/WHEEL
Netbyte-0.1.6.3.dist-info/top_level.txt
netbyte/__init__.py
netbyte/__main__.py
netbyte/compile.py
netbyte/empty.nbe
netbyte/main.py
