Metadata-Version: 2.1
Name: Netbyte
Version: 0.1.6.3
Summary: A language with interpreter and compiler: silk flexibility with network level versatility!
Home-page: https://github.com/Gustavo6046/Netbyte
Author: Gustavo6046
Author-email: gugurehermann@gmail.com
License: MIT
Keywords: compiler language interpreter bytecode
Platform: UNKNOWN
